odoo10_addon_pos_order_remove_line-10.0.1.0.1-py3.8-nspkg.pth
odoo/addons/pos_order_remove_line/README.rst
odoo/addons/pos_order_remove_line/__init__.py
odoo/addons/pos_order_remove_line/__manifest__.py
odoo/addons/pos_order_remove_line/i18n/ca.po
odoo/addons/pos_order_remove_line/i18n/es.po
odoo/addons/pos_order_remove_line/i18n/pos_order_remove_line.pot
odoo/addons/pos_order_remove_line/readme/CONTRIBUTORS.rst
odoo/addons/pos_order_remove_line/readme/DESCRIPTION.rst
odoo/addons/pos_order_remove_line/static/description/icon.png
odoo/addons/pos_order_remove_line/static/description/index.html
odoo/addons/pos_order_remove_line/static/src/js/order_line.js
odoo/addons/pos_order_remove_line/static/src/less/order_line.less
odoo/addons/pos_order_remove_line/static/src/xml/order_line.xml
odoo/addons/pos_order_remove_line/views/assets.xml
odoo10_addon_pos_order_remove_line-10.0.1.0.1.dist-info/METADATA
odoo10_addon_pos_order_remove_line-10.0.1.0.1.dist-info/WHEEL
odoo10_addon_pos_order_remove_line-10.0.1.0.1.dist-info/namespace_packages.txt
odoo10_addon_pos_order_remove_line-10.0.1.0.1.dist-info/top_level.txt
odoo10_addon_pos_order_remove_line-10.0.1.0.1.dist-info/RECORD
